funtable/__init__.py
funtable/kv/__init__.py
funtable/kv/interface.py
funtable/kv/sqlite_table.py
funtable/kv/tinydb_table.py
funtable/snapshot/__init__.py
funtable/snapshot/core.py
funtable/sqlmodel/__init__.py
funtable/sqlmodel/base.py
funtable/table/__init__.py
funtable/table/drive.py
funtable-1.0.41.dist-info/METADATA
funtable-1.0.41.dist-info/WHEEL
funtable-1.0.41.dist-info/top_level.txt
funtable-1.0.41.dist-info/RECORD
