Metadata-Version: 2.4
Name: funtable
Version: 1.0.41
Summary: A unified table storage abstraction library with support for multiple backends
Author-email: 牛哥 <niuliangtao@qq.com>, farfarfun <farfarfun@qq.com>
Maintainer-email: 牛哥 <niuliangtao@qq.com>, farfarfun <farfarfun@qq.com>
License: MIT
Project-URL: Organization, https://github.com/farfarfun
Project-URL: Repository, https://github.com/farfarfun/funtable
Project-URL: Releases, https://github.com/farfarfun/funtable/releases
Keywords: table,storage,database,kv,key-value,sqlite,tinydb,sqlmodel,orm,abstraction
Classifier: Development Status :: 4 - Beta
Classifier: Intended Audience :: Developers
Classifier: License :: OSI Approved :: MIT License
Classifier: Operating System :: OS Independent
Classifier: Programming Language :: Python :: 3
Classifier: Programming Language :: Python :: 3.8
Classifier: Programming Language :: Python :: 3.9
Classifier: Programming Language :: Python :: 3.10
Classifier: Programming Language :: Python :: 3.11
Classifier: Programming Language :: Python :: 3.12
Classifier: Topic :: Database
Classifier: Topic :: Software Development :: Libraries :: Python Modules
Classifier: Topic :: System :: Archiving :: Backup
Classifier: Typing :: Typed
Requires-Python: >=3.8
Requires-Dist: funutil>=1.0.5
Provides-Extra: sqlmodel
Requires-Dist: sqlmodel>=0.0.24; extra == "sqlmodel"
Requires-Dist: sqlalchemy>=1.4.0; extra == "sqlmodel"
Provides-Extra: snapshot
Requires-Dist: fundrive>=2.0.8; extra == "snapshot"
Requires-Dist: funfile; extra == "snapshot"
Provides-Extra: kv
Requires-Dist: tinydb>=4.8.2; extra == "kv"
Provides-Extra: dev
Requires-Dist: pytest>=7.0.0; extra == "dev"
Requires-Dist: pytest-cov>=4.0.0; extra == "dev"
Requires-Dist: black>=22.0.0; extra == "dev"
Requires-Dist: isort>=5.10.0; extra == "dev"
Requires-Dist: flake8>=5.0.0; extra == "dev"
Requires-Dist: mypy>=1.0.0; extra == "dev"
Requires-Dist: pre-commit>=2.20.0; extra == "dev"
Provides-Extra: all
Requires-Dist: funtable[kv,snapshot,sqlmodel]; extra == "all"
